setup.cfg
setup.py
cdata/cdata.pycore.snowflake.jar
cdata/jre.tar.gz
cdata/snowflake.cpython-310-x86_64-linux-gnu.so
cdata/snowflake.cpython-37m-x86_64-linux-gnu.so
cdata/snowflake.cpython-38-x86_64-linux-gnu.so
cdata/snowflake.cpython-39-x86_64-linux-gnu.so
cdata/snowflakecleanup.sh
cdata/snowflakertutil.sh
cdata/installlic_snowflake/install-license.sh
cdata/sqlalchemy_snowflake/__init__.py
cdata/sqlalchemy_snowflake/base.py
cdata/sqlalchemy_snowflake/dialect.py
cdata/sqlalchemy_snowflake/log.py
cdata/sqlalchemy_snowflake/types.py
cdata_snowflake_connector.egg-info/PKG-INFO
cdata_snowflake_connector.egg-info/SOURCES.txt
cdata_snowflake_connector.egg-info/dependency_links.txt
cdata_snowflake_connector.egg-info/entry_points.txt
cdata_snowflake_connector.egg-info/top_level.txt